hdl/rtl/PROG_CNTR.sv
/* 
    Module PROG_CNTR: 32 bit Register

    Instantiation Template:

    // START: PROG_CNTR
    PROG_CNTR #(.XLEN(32))
    PROGRAM_COUNTER(
        .CLK(),
        .RST(),
        .LOAD(),
        .PC_IN(),
        .PC_OUT()
    );
    // END: PROG_CNTR
*/

`timescale 1ns/1ps

module PROG_CNTR
#(parameter XLEN = 32)
(
    input CLK,
    input RST,
    input LOAD,
    input [XLEN-1:0] PC_IN,
    output [XLEN-1:0] PC_OUT
);

    always_ff@(posdege CLK)
        if(RST)
            PC_OUT <= 0;
        else if(LOAD)
            PC_OUT <= PC_IN;
            
endmodule

hdl/rtl/IMEM.sv
/*
    Module: Instruction Memory 24kb

    Instantiation Template: 

        // START: IMEM
        IMEM INSTRUCTION_MEMORY(
            .CLK(),
            .IR_RD_EN(), 
            .IR_ADDR(), // ADDR = 2^10 (6144 words)
            .IR_OUT(),
            .INVALID_ACCESS()
        );

*/

`timescale 1ns/1ps
/* verilator lint_off MULTITOP */
module IMEM
(
    input CLK,
    input IR_RD_EN,
    input [12:0] IR_ADDR,
    output logic [31:0] IR_OUT,
    output logic INVALID_ACCESS
);

    logic EACCESS;
    logic [31:0] instruction_memory_24kb [0:6143];

    initial begin 
        $readmemh("prog.mem", instruction_memory_24kb);
    end
    
    assign EACCESS = (IR_ADDR > 13'd6143); // (24kb / 4 bytes) = 6144 words

    always_ff@(posedge CLK) begin
        if(IR_RD_EN) begin
            if(EACCESS) begin
                IR_OUT <= 32'hdeadbeef;
                INVALID_ACCESS <= 1;
            end else begin
                IR_OUT <= instruction_memory_24kb[IR_ADDR];
                INVALID_ACCESS <= 0;
            end
        end
    end

endmodule

hdl/sim/tb_INSTRUCTION_FEED/INSTRUCTION_FEED.sv
`timescale 1ns/1ps

module INSTRUCTION_FEED(
    input clk,
    input hold,
    input rst
);

    logic [31:0] pc_in, pc_out, ir;
    logic inv_err;

    assign pc_in = pc_out + 4;
    
    IMEM INSTRUCTION_MEMORY(
        .CLK(clk),
        .IR_RD_EN(1'b1), 
        .IR_ADDR(pc_out[14:2]), // ADDR = 2^10 (6144 words)
        .IR_OUT(ir),
        .INVALID_ACCESS(inv_err)
    );

    PROG_CNTR #(.XLEN(32))
    PROGRAM_COUNTER(
        .CLK(clk),
        .RST(rst),
        .LOAD(~hold),
        .PC_IN(pc_in),
        .PC_OUT(pc_out)
    );
endmodule

hdl/sim/tb_INSTRUCTION_FEED/tb_INSTRUCTION_FEED.sv
`timescale 1ns/1ps

module tb_INSTRUCTION_FEED;

    logic tb_clk;
    logic tb_rst;
    logic tb_hold;

    INSTRUCTION_FEED DUT(
        .clk(tb_clk),
        .hold(tb_hold),
        .rst(tb_rst)
    );

    initial begin
        $dumpfile("tb_INSTRUCTION_FEED.vcd");
        $dumpvars(0, tb_INSTRUCTION_FEED);
    end

    initial begin
        tb_clk = 1'b0;
        forever #5 tb_clk = ~tb_clk;
    end

    initial begin
        tb_rst = 1'b1;
        tb_hold = 1'b0;
    end

    initial begin
        #10;
        tb_rst = 1'b0;
        #20;
        tb_hold = 1'b1;
        #10;
        tb_hold = 1'b0;
        #1000;
        $finish;
    end



endmodule

hdl/sim/tb_INSTRUCTION_FEED/tb_INSTRUCTION_FEED.vcd
$date
	Fri Mar 13 01:07:32 2026
$end
$version
	Icarus Verilog
$end
$timescale
	1ps
$end
$scope module tb_INSTRUCTION_FEED $end
$var reg 1 ! tb_clk $end
$var reg 1 " tb_hold $end
$var reg 1 # tb_rst $end
$scope module DUT $end
$var wire 1 ! clk $end
$var wire 1 " hold $end
$var wire 1 # rst $end
$var wire 32 $ pc_out [31:0] $end
$var wire 32 % pc_in [31:0] $end
$var wire 32 & ir [31:0] $end
$var wire 1 ' inv_err $end
$scope module INSTRUCTION_MEMORY $end
$var wire 1 ! CLK $end
$var wire 13 ( IR_ADDR [12:0] $end
$var wire 1 ) IR_RD_EN $end
$var wire 1 * EACCESS $end
$var reg 1 ' INVALID_ACCESS $end
$var reg 32 + IR_OUT [31:0] $end
$upscope $end
$scope module PROGRAM_COUNTER $end
$var wire 1 ! CLK $end
$var wire 1 , LOAD $end
$var wire 32 - PC_IN [31:0] $end
$var wire 1 # RST $end
$var parameter 32 . XLEN $end
$var reg 32 / PC_OUT [31:0] $end
$upscope $end
$upscope $end
$upscope $end
$enddefinitions $end
$comment Show the parameter values. $end
$dumpall
b100000 .
$end
#0
$dumpvars
bx /
bx -
1,
bx +
x*
1)
bx (
x'
bx &
bx %
bx $
1#
0"
0!
$end
#5000
0*
b0 (
0'
b100 %
b100 -
b0 $
b0 /
1!
#10000
0!
0#
#15000
b1 (
b1000 %
b1000 -
b100 $
b100 /
b110010000000000000010010011 &
b110010000000000000010010011 +
1!
#20000
0!
#25000
b10 (
b1010000000000000100010011 &
b1010000000000000100010011 +
b1100 %
b1100 -
b1000 $
b1000 /
1!
#30000
0,
0!
1"
#35000
b10000011001100011 &
b10000011001100011 +
1!
#40000
1,
0!
0"
#45000
b11 (
b10000 %
b10000 -
b1100 $
b1100 /
1!
#50000
0!
#55000
b100 (
b10100 %
b10100 -
b10000 $
b10000 /
b11111111111100010000000100010011 &
b11111111111100010000000100010011 +
1!
#60000
0!
#65000
b101 (
b110010000001000000010010011 &
b110010000001000000010010011 +
b11000 %
b11000 -
b10100 $
b10100 /
1!
#70000
0!
#75000
b110 (
b11100 %
b11100 -
b11000 $
b11000 /
b100000000000110010011 &
b100000000000110010011 +
1!
#80000
0!
#85000
b111 (
bx &
bx +
b100000 %
b100000 -
b11100 $
b11100 /
1!
#90000
0!
#95000
b1000 (
b100100 %
b100100 -
b100000 $
b100000 /
1!
#100000
0!
#105000
b1001 (
b101000 %
b101000 -
b100100 $
b100100 /
1!
#110000
0!
#115000
b1010 (
b101100 %
b101100 -
b101000 $
b101000 /
1!
#120000
0!
#125000
b1011 (
b110000 %
b110000 -
b101100 $
b101100 /
1!
#130000
0!
#135000
b1100 (
b110100 %
b110100 -
b110000 $
b110000 /
1!
#140000
0!
#145000
b1101 (
b111000 %
b111000 -
b110100 $
b110100 /
1!
#150000
0!
#155000
b1110 (
b111100 %
b111100 -
b111000 $
b111000 /
1!
#160000
0!
#165000
b1111 (
b1000000 %
b1000000 -
b111100 $
b111100 /
1!
#170000
0!
#175000
b10000 (
b1000100 %
b1000100 -
b1000000 $
b1000000 /
1!
#180000
0!
#185000
b10001 (
b1001000 %
b1001000 -
b1000100 $
b1000100 /
1!
#190000
0!
#195000
b10010 (
b1001100 %
b1001100 -
b1001000 $
b1001000 /
1!
#200000
0!
#205000
b10011 (
b1010000 %
b1010000 -
b1001100 $
b1001100 /
1!
#210000
0!
#215000
b10100 (
b1010100 %
b1010100 -
b1010000 $
b1010000 /
1!
#220000
0!
#225000
b10101 (
b1011000 %
b1011000 -
b1010100 $
b1010100 /
1!
#230000
0!
#235000
b10110 (
b1011100 %
b1011100 -
b1011000 $
b1011000 /
1!
#240000
0!
#245000
b10111 (
b1100000 %
b1100000 -
b1011100 $
b1011100 /
1!
#250000
0!
#255000
b11000 (
b1100100 %
b1100100 -
b1100000 $
b1100000 /
1!
#260000
0!
#265000
b11001 (
b1101000 %
b1101000 -
b1100100 $
b1100100 /
1!
#270000
0!
#275000
b11010 (
b1101100 %
b1101100 -
b1101000 $
b1101000 /
1!
#280000
0!
#285000
b11011 (
b1110000 %
b1110000 -
b1101100 $
b1101100 /
1!
#290000
0!
#295000
b11100 (
b1110100 %
b1110100 -
b1110000 $
b1110000 /
1!
#300000
0!
#305000
b11101 (
b1111000 %
b1111000 -
b1110100 $
b1110100 /
1!
#310000
0!
#315000
b11110 (
b1111100 %
b1111100 -
b1111000 $
b1111000 /
1!
#320000
0!
#325000
b11111 (
b10000000 %
b10000000 -
b1111100 $
b1111100 /
1!
#330000
0!
#335000
b100000 (
b10000100 %
b10000100 -
b10000000 $
b10000000 /
1!
#340000
0!
#345000
b100001 (
b10001000 %
b10001000 -
b10000100 $
b10000100 /
1!
#350000
0!
#355000
b100010 (
b10001100 %
b10001100 -
b10001000 $
b10001000 /
1!
#360000
0!
#365000
b100011 (
b10010000 %
b10010000 -
b10001100 $
b10001100 /
1!
#370000
0!
#375000
b100100 (
b10010100 %
b10010100 -
b10010000 $
b10010000 /
1!
#380000
0!
#385000
b100101 (
b10011000 %
b10011000 -
b10010100 $
b10010100 /
1!
#390000
0!
#395000
b100110 (
b10011100 %
b10011100 -
b10011000 $
b10011000 /
1!
#400000
0!
#405000
b100111 (
b10100000 %
b10100000 -
b10011100 $
b10011100 /
1!
#410000
0!
#415000
b101000 (
b10100100 %
b10100100 -
b10100000 $
b10100000 /
1!
#420000
0!
#425000
b101001 (
b10101000 %
b10101000 -
b10100100 $
b10100100 /
1!
#430000
0!
#435000
b101010 (
b10101100 %
b10101100 -
b10101000 $
b10101000 /
1!
#440000
0!
#445000
b101011 (
b10110000 %
b10110000 -
b10101100 $
b10101100 /
1!
#450000
0!
#455000
b101100 (
b10110100 %
b10110100 -
b10110000 $
b10110000 /
1!
#460000
0!
#465000
b101101 (
b10111000 %
b10111000 -
b10110100 $
b10110100 /
1!
#470000
0!
#475000
b101110 (
b10111100 %
b10111100 -
b10111000 $
b10111000 /
1!
#480000
0!
#485000
b101111 (
b11000000 %
b11000000 -
b10111100 $
b10111100 /
1!
#490000
0!
#495000
b110000 (
b11000100 %
b11000100 -
b11000000 $
b11000000 /
1!
#500000
0!
#505000
b110001 (
b11001000 %
b11001000 -
b11000100 $
b11000100 /
1!
#510000
0!
#515000
b110010 (
b11001100 %
b11001100 -
b11001000 $
b11001000 /
1!
#520000
0!
#525000
b110011 (
b11010000 %
b11010000 -
b11001100 $
b11001100 /
1!
#530000
0!
#535000
b110100 (
b11010100 %
b11010100 -
b11010000 $
b11010000 /
1!
#540000
0!
#545000
b110101 (
b11011000 %
b11011000 -
b11010100 $
b11010100 /
1!
#550000
0!
#555000
b110110 (
b11011100 %
b11011100 -
b11011000 $
b11011000 /
1!
#560000
0!
#565000
b110111 (
b11100000 %
b11100000 -
b11011100 $
b11011100 /
1!
#570000
0!
#575000
b111000 (
b11100100 %
b11100100 -
b11100000 $
b11100000 /
1!
#580000
0!
#585000
b111001 (
b11101000 %
b11101000 -
b11100100 $
b11100100 /
1!
#590000
0!
#595000
b111010 (
b11101100 %
b11101100 -
b11101000 $
b11101000 /
1!
#600000
0!
#605000
b111011 (
b11110000 %
b11110000 -
b11101100 $
b11101100 /
1!
#610000
0!
#615000
b111100 (
b11110100 %
b11110100 -
b11110000 $
b11110000 /
1!
#620000
0!
#625000
b111101 (
b11111000 %
b11111000 -
b11110100 $
b11110100 /
1!
#630000
0!
#635000
b111110 (
b11111100 %
b11111100 -
b11111000 $
b11111000 /
1!
#640000
0!
#645000
b111111 (
b100000000 %
b100000000 -
b11111100 $
b11111100 /
1!
#650000
0!
#655000
b1000000 (
b100000100 %
b100000100 -
b100000000 $
b100000000 /
1!
#660000
0!
#665000
b1000001 (
b100001000 %
b100001000 -
b100000100 $
b100000100 /
1!
#670000
0!
#675000
b1000010 (
b100001100 %
b100001100 -
b100001000 $
b100001000 /
1!
#680000
0!
#685000
b1000011 (
b100010000 %
b100010000 -
b100001100 $
b100001100 /
1!
#690000
0!
#695000
b1000100 (
b100010100 %
b100010100 -
b100010000 $
b100010000 /
1!
#700000
0!
#705000
b1000101 (
b100011000 %
b100011000 -
b100010100 $
b100010100 /
1!
#710000
0!
#715000
b1000110 (
b100011100 %
b100011100 -
b100011000 $
b100011000 /
1!
#720000
0!
#725000
b1000111 (
b100100000 %
b100100000 -
b100011100 $
b100011100 /
1!
#730000
0!
#735000
b1001000 (
b100100100 %
b100100100 -
b100100000 $
b100100000 /
1!
#740000
0!
#745000
b1001001 (
b100101000 %
b100101000 -
b100100100 $
b100100100 /
1!
#750000
0!
#755000
b1001010 (
b100101100 %
b100101100 -
b100101000 $
b100101000 /
1!
#760000
0!
#765000
b1001011 (
b100110000 %
b100110000 -
b100101100 $
b100101100 /
1!
#770000
0!
#775000
b1001100 (
b100110100 %
b100110100 -
b100110000 $
b100110000 /
1!
#780000
0!
#785000
b1001101 (
b100111000 %
b100111000 -
b100110100 $
b100110100 /
1!
#790000
0!
#795000
b1001110 (
b100111100 %
b100111100 -
b100111000 $
b100111000 /
1!
#800000
0!
#805000
b1001111 (
b101000000 %
b101000000 -
b100111100 $
b100111100 /
1!
#810000
0!
#815000
b1010000 (
b101000100 %
b101000100 -
b101000000 $
b101000000 /
1!
#820000
0!
#825000
b1010001 (
b101001000 %
b101001000 -
b101000100 $
b101000100 /
1!
#830000
0!
#835000
b1010010 (
b101001100 %
b101001100 -
b101001000 $
b101001000 /
1!
#840000
0!
#845000
b1010011 (
b101010000 %
b101010000 -
b101001100 $
b101001100 /
1!
#850000
0!
#855000
b1010100 (
b101010100 %
b101010100 -
b101010000 $
b101010000 /
1!
#860000
0!
#865000
b1010101 (
b101011000 %
b101011000 -
b101010100 $
b101010100 /
1!
#870000
0!
#875000
b1010110 (
b101011100 %
b101011100 -
b101011000 $
b101011000 /
1!
#880000
0!
#885000
b1010111 (
b101100000 %
b101100000 -
b101011100 $
b101011100 /
1!
#890000
0!
#895000
b1011000 (
b101100100 %
b101100100 -
b101100000 $
b101100000 /
1!
#900000
0!
#905000
b1011001 (
b101101000 %
b101101000 -
b101100100 $
b101100100 /
1!
#910000
0!
#915000
b1011010 (
b101101100 %
b101101100 -
b101101000 $
b101101000 /
1!
#920000
0!
#925000
b1011011 (
b101110000 %
b101110000 -
b101101100 $
b101101100 /
1!
#930000
0!
#935000
b1011100 (
b101110100 %
b101110100 -
b101110000 $
b101110000 /
1!
#940000
0!
#945000
b1011101 (
b101111000 %
b101111000 -
b101110100 $
b101110100 /
1!
#950000
0!
#955000
b1011110 (
b101111100 %
b101111100 -
b101111000 $
b101111000 /
1!
#960000
0!
#965000
b1011111 (
b110000000 %
b110000000 -
b101111100 $
b101111100 /
1!
#970000
0!
#975000
b1100000 (
b110000100 %
b110000100 -
b110000000 $
b110000000 /
1!
#980000
0!
#985000
b1100001 (
b110001000 %
b110001000 -
b110000100 $
b110000100 /
1!
#990000
0!
#995000
b1100010 (
b110001100 %
b110001100 -
b110001000 $
b110001000 /
1!
#1000000
0!
#1005000
b1100011 (
b110010000 %
b110010000 -
b110001100 $
b110001100 /
1!
#1010000
0!
#1015000
b1100100 (
b110010100 %
b110010100 -
b110010000 $
b110010000 /
1!
#1020000
0!
#1025000
b1100101 (
b110011000 %
b110011000 -
b110010100 $
b110010100 /
1!
#1030000
0!
#1035000
b1100110 (
b110011100 %
b110011100 -
b110011000 $
b110011000 /
1!
